disk_monitor/__init__.py
disk_monitor/alert.py
disk_monitor/disk_usage.py
disk_monitor/version.py
disk_monitor_demo1-1.0.2.dist-info/METADATA
disk_monitor_demo1-1.0.2.dist-info/WHEEL
disk_monitor_demo1-1.0.2.dist-info/top_level.txt
disk_monitor_demo1-1.0.2.dist-info/RECORD
