Metadata-Version: 2.1
Name: disk_monitor_demo1
Version: 1.0.2
Summary: Module de surveillance d'espace disque pour Linux
Home-page: https://github.com/votrecompte/disk_monitor
Author: Aurélien D
Author-email: aurelien.dazy@wildcodeschool.com
Classifier: Programming Language :: Python :: 3
Classifier: License :: OSI Approved :: MIT License
Classifier: Operating System :: OS Independent
Requires-Python: >=3.11
